{
  "parent": "minecraft:recipes/root",
  "rewards": {
    "recipes": [
      "zeboncraft:dried_polished_zrirt"
    ]
  },
  "criteria": {
    "item": {
      "trigger": "minecraft:inventory_changed",
      "conditions": {
        "items": [
          {
            "item": "zeboncraft:dried_zrirt"
          }
        ]
      }
    },
    "has_the_recipe": {
      "trigger": "minecraft:recipe_unlocked",
      "conditions": {
        "recipe": "zeboncraft:dried_polished_zrirt"
      }
    }
  },
  "requirements": [
    [
      "item",
      "has_the_recipe"
    ]
  ]
}